valueobject/__init__.py
valueobject/tests/__init__.py
valueobject/tests/value_object_test.py
valueobject-1.0.3.dist-info/LICENSE
valueobject-1.0.3.dist-info/METADATA
valueobject-1.0.3.dist-info/WHEEL
valueobject-1.0.3.dist-info/top_level.txt
valueobject-1.0.3.dist-info/RECORD
