Metadata-Version: 2.1
Name: valueobject
Version: 1.0.3
Summary: ValueObject is a dict-like object that exposes keys as attributes.
Home-page: https://github.com/rbu/valueobject
Author: Felix Schwarz, Martin Häcker, Robert Buchholz
Author-email: rbu@goodpoint.de, spamfaenger@gmx.de
License: ISC
Classifier: Development Status :: 5 - Production/Stable
Classifier: Topic :: Software Development :: Libraries :: Python Modules
Classifier: Intended Audience :: Developers
Classifier: License :: OSI Approved :: ISC License (ISCL)
Classifier: Programming Language :: Python
Classifier: Programming Language :: Python :: 2.7
Classifier: Programming Language :: Python :: 3
License-File: LICENSE
Provides-Extra: testing
Requires-Dist: PythonicTestcase ; extra == 'testing'
